tno.mpc.mpyc.statistics-0.1.1-py3.8-nspkg.pth
tno/mpc/mpyc/statistics/__init__.py
tno/mpc/mpyc/statistics/py.typed
tno/mpc/mpyc/statistics/statistics.py
tno/mpc/mpyc/statistics/test/__init__.py
tno/mpc/mpyc/statistics/test/test_statistics.py
tno/mpc/mpyc/statistics/test/test_utils.py
tno/mpc/mpyc/statistics/utils/__init__.py
tno/mpc/mpyc/statistics/utils/types.py
tno/mpc/mpyc/statistics/utils/utils.py
tno.mpc.mpyc.statistics-0.1.1.dist-info/LICENSE
tno.mpc.mpyc.statistics-0.1.1.dist-info/METADATA
tno.mpc.mpyc.statistics-0.1.1.dist-info/WHEEL
tno.mpc.mpyc.statistics-0.1.1.dist-info/namespace_packages.txt
tno.mpc.mpyc.statistics-0.1.1.dist-info/top_level.txt
tno.mpc.mpyc.statistics-0.1.1.dist-info/RECORD
