Metadata-Version: 2.1
Name: tno.mpc.mpyc.statistics
Version: 0.1.1
Summary: Secure Data Exploratory Analyses on Vertically Partitioned Data
Home-page: https://mpc.tno.nl/
Author: TNO MPC Lab
Author-email: mpclab@tno.nl
Maintainer: TNO MPC Lab
Maintainer-email: mpclab@tno.nl
License: Apache License, Version 2.0
Download-URL: https://pypi.org/project/tno.mpc.mpyc.statistics/#files
Project-URL: Documentation, https://docs.mpc.tno.nl/mpyc/statistics/0.1.1
Project-URL: Source Code, https://github.com/TNO-MPC/mpyc.statistics
Keywords: TNO,MPC,multi-party computation,secure learning,statistics,mean,median,min_max,frequency,contingency tables,unique values,covariance,correlation,interquartile range
Platform: any
Classifier: License :: OSI Approved :: Apache Software License
Classifier: Programming Language :: Python :: 3
Classifier: Operating System :: OS Independent
Classifier: Intended Audience :: Developers
Classifier: Intended Audience :: Information Technology
Classifier: Intended Audience :: Science/Research
Classifier: Typing :: Typed
Classifier: Topic :: Security :: Cryptography
Classifier: Topic :: Scientific/Engineering :: Information Analysis
License-File: LICENSE
Requires-Dist: mpyc
Requires-Dist: numpy
Requires-Dist: tno.mpc.mpyc.stubs (~=0.7.0)
Requires-Dist: typing-extensions
Provides-Extra: gmpy
Requires-Dist: gmpy2 (>=2.1.0) ; extra == 'gmpy'
Provides-Extra: tests
Requires-Dist: pytest ; extra == 'tests'
Requires-Dist: pytest-asyncio ; extra == 'tests'
Requires-Dist: pandas ; extra == 'tests'
